samruddhk/__init__.py
samruddhk/bfs.py
samruddhk/dfs.py
samruddhk/dijkstra.py
samruddhk/hillclimbing.py
samruddhk/kruskal.py
samruddhk/statistics.py
samruddhk/topo.py
samruddhk/towerofhanoi.py
samruddhk/travellingsalseman.py
samruddhk/warshall.py
samruddhk-2.2.19.dist-info/METADATA
samruddhk-2.2.19.dist-info/WHEEL
samruddhk-2.2.19.dist-info/top_level.txt
samruddhk-2.2.19.dist-info/RECORD
