Metadata-Version: 2.4
Name: samruddhk
Version: 2.2.19
Summary: A collection of algorithms
Author-email: SAMRUDDH K <samruddh.k52@gmail.com>
License: MIT
Project-URL: Homepage, https://github.com/SAMRUDDH15/samruddhk
Requires-Python: >=3.6
